flask_error_templating/__init__.py
flask_error_templating/main.py
flask_error_templating-1.1.1.dist-info/LICENSE
flask_error_templating-1.1.1.dist-info/METADATA
flask_error_templating-1.1.1.dist-info/WHEEL
flask_error_templating-1.1.1.dist-info/top_level.txt
flask_error_templating-1.1.1.dist-info/RECORD
