Metadata-Version: 2.1
Name: flask-error-templating
Version: 1.1.1
Summary: Create Flask HTTP error handlers that use template rendering.
Home-page: https://github.com/that-cool-coder/flask-error-templating
Author: ThatCoolCoder
License: UNKNOWN
Project-URL: Bug Tracker, https://github.com/that-cool-coder/flask-error-templating/issues
Platform: UNKNOWN
Classifier: Programming Language :: Python :: 3
Classifier: License :: OSI Approved :: MIT License
Classifier: Operating System :: OS Independent
Requires-Python: >=3.7
License-File: LICENSE
